vappman/AppimageDoctor.py
vappman/AppmanLauncher.py
vappman/AppmanVars.py
vappman/CommandRunner.py
vappman/PersistentState.py
vappman/Prerequisites.py
vappman/VappmanListCache.py
vappman/__init__.py
vappman/main.py
vappman-2.1.4.dist-info/entry_points.txt
vappman-2.1.4.dist-info/licenses/LICENSE
vappman-2.1.4.dist-info/WHEEL
vappman-2.1.4.dist-info/METADATA
vappman-2.1.4.dist-info/RECORD
