Metadata-Version: 2.4
Name: vappman
Version: 2.1.4
Summary: A visual wrapper for appman
Keywords: app,installer,manager,appimages
Author-email: Joe Defen <joedef@google.com>
Requires-Python: >=3.8
Classifier: Programming Language :: Python :: 3
Classifier: License :: OSI Approved :: MIT License
Classifier: Operating System :: POSIX :: Linux
License-File: LICENSE
Requires-Dist: console-window == 1.3.2
Project-URL: Bug Tracker, https://github.com/joedefen/vappman/issues
Project-URL: Homepage, https://github.com/joedefen/vappman
